{
    "counties": [
        { "id": "barbour", "label": "Barbour", "pilot": false, "apprenticeship": false },
        { "id": "berkeley", "label": "Berkeley", "pilot": true, "apprenticeship": false },
        { "id": "boone", "label": "Boone", "pilot": false, "apprenticeship": false },
        { "id": "braxton", "label": "Braxton", "pilot": true, "apprenticeship": false },
        { "id": "brooke", "label": "Brooke", "pilot": true, "apprenticeship": false },
        { "id": "cabell", "label": "Cabell", "pilot": true, "apprenticeship": false },
        { "id": "calhoun", "label": "Calhoun", "pilot": true, "apprenticeship": false },
        { "id": "clay", "label": "Clay", "pilot": false, "apprenticeship": false },
        { "id": "doddridge", "label": "Doddridge", "pilot": false, "apprenticeship": false },
        { "id": "fayette", "label": "Fayette", "pilot": true, "apprenticeship": true },
        { "id": "gilmer", "label": "Gilmer", "pilot": false, "apprenticeship": false },
        { "id": "grant", "label": "Grant", "pilot": true, "apprenticeship": false },
        { "id": "greenbrier", "label": "Greenbrier", "pilot": true, "apprenticeship": false },
        { "id": "hampshire", "label": "Hampshire", "pilot": true, "apprenticeship": false },
        { "id": "hancock", "label": "Hancock", "pilot": false, "apprenticeship": false },
        { "id": "hardy", "label": "Hardy", "pilot": true, "apprenticeship": true },
        { "id": "harrison", "label": "Harrison", "pilot": false, "apprenticeship": false },
        { "id": "jackson", "label": "Jackson", "pilot": true, "apprenticeship": false },
        { "id": "jefferson", "label": "Jefferson", "pilot": true, "apprenticeship": false },
        { "id": "kanawha", "label": "Kanawha", "pilot": true, "apprenticeship": false },
        { "id": "lewis", "label": "Lewis", "pilot": true, "apprenticeship": true },
        { "id": "lincoln", "label": "Lincoln", "pilot": false, "apprenticeship": false },
        { "id": "logan", "label": "Logan", "pilot": true, "apprenticeship": false },
        { "id": "marion", "label": "Marion", "pilot": false, "apprenticeship": false },
        { "id": "marshall", "label": "Marshall", "pilot": true, "apprenticeship": true },
        { "id": "mason", "label": "Mason", "pilot": true, "apprenticeship": false },
        { "id": "mcdowell", "label": "Mcdowell", "pilot": true, "apprenticeship": false },
        { "id": "mercer", "label": "Mercer", "pilot": true, "apprenticeship": true },
        { "id": "mineral", "label": "Mineral", "pilot": false, "apprenticeship": false },
        { "id": "mingo", "label": "Mingo", "pilot": true, "apprenticeship": false },
        { "id": "monongalia", "label": "Monongalia", "pilot": false, "apprenticeship": false },
        { "id": "monroe", "label": "Monroe", "pilot": true, "apprenticeship": false },
        { "id": "morgan", "label": "Morgan", "pilot": false, "apprenticeship": false },
        { "id": "nicholas", "label": "Nicholas", "pilot": true, "apprenticeship": false },
        { "id": "ohio", "label": "Ohio", "pilot": true, "apprenticeship": true },
        { "id": "pendleton", "label": "Pendleton", "pilot": true, "apprenticeship": false },
        { "id": "pleasants", "label": "Pleasants", "pilot": true, "apprenticeship": false },
        { "id": "pocahontas", "label": "Pocahontas", "pilot": true, "apprenticeship": true },
        { "id": "preston", "label": "Preston", "pilot": false, "apprenticeship": false },
        { "id": "putnam", "label": "Putnam", "pilot": true, "apprenticeship": false },
        { "id": "raleigh", "label": "Raleigh", "pilot": false, "apprenticeship": false },
        { "id": "randolph", "label": "Randolph", "pilot": true, "apprenticeship": false },
        { "id": "ritchie", "label": "Ritchie", "pilot": false, "apprenticeship": false },
        { "id": "roane", "label": "Roane", "pilot": false, "apprenticeship": false },
        { "id": "summers", "label": "Summers", "pilot": true, "apprenticeship": false },
        { "id": "taylor", "label": "Taylor", "pilot": false, "apprenticeship": false },
        { "id": "tucker", "label": "Tucker", "pilot": false, "apprenticeship": false },
        { "id": "tyler", "label": "Tyler", "pilot": true, "apprenticeship": false },
        { "id": "upshur", "label": "Upshur", "pilot": true, "apprenticeship": true },
        { "id": "wayne", "label": "Wayne", "pilot": true, "apprenticeship": false },
        { "id": "webster", "label": "Webster", "pilot": true, "apprenticeship": false },
        { "id": "wetzel", "label": "Wetzel", "pilot": false, "apprenticeship": false },
        { "id": "wirt", "label": "Wirt", "pilot": false, "apprenticeship": false },
        { "id": "wood", "label": "Wood", "pilot": false, "apprenticeship": false },
        { "id": "wyoming", "label": "Wyoming", "pilot": false, "apprenticeship": false }
    ],
    "labels": [
        {
            "id": "pilot", 
            "title": "Pilot",
            "style": { "background": "#3579AA" }
        },
        {
            "id": "apprenticeship",
            "title": "Pilot and Apprenticeship",
            "style": { "background": "#e6ae18" }
        }
    ]
}